just_a_test_project/__init__.py
just_a_test_project/module1.py
just_a_test_project/package1/__init__.py
just_a_test_project/package1/module_in_pkg.py
just_a_test_project/py.typed
just_a_test_project-0.0.30.dist-info/WHEEL
just_a_test_project-0.0.30.dist-info/METADATA
just_a_test_project-0.0.30.dist-info/RECORD
