Metadata-Version: 2.1
Name: just-a-test-project
Version: 0.0.30
Summary: A project for testing https://github.com/creditornot/wolt-python-package-cookiecutter
Home-page: https://creditornot.github.io/just-a-test-project
License: MIT
Author: Jerry Pussinen
Author-email: jerry.pussinen@gmail.com
Requires-Python: >=3.7.1,<4.0
Classifier: Development Status :: 4 - Beta
Classifier: Intended Audience :: Developers
Classifier: License :: OSI Approved :: MIT License
Classifier: Operating System :: OS Independent
Classifier: Programming Language :: Python
Classifier: Programming Language :: Python :: 3
Classifier: Programming Language :: Python :: 3.7
Classifier: Programming Language :: Python :: 3.8
Classifier: Programming Language :: Python :: 3.9
Classifier: Topic :: Software Development :: Libraries :: Python Modules
Classifier: Typing :: Typed
Project-URL: Documentation, https://creditornot.github.io/just-a-test-project
Project-URL: Repository, https://github.com/creditornot/just-a-test-project
